topfm/__about__.py
topfm/__init__.py
topfm/__main__.py
topfm/collage.py
topfm/lastfm.py
topfm/unknown-cover.jpg
TopFM-0.9.2.dist-info/LICENSE
TopFM-0.9.2.dist-info/METADATA
TopFM-0.9.2.dist-info/WHEEL
TopFM-0.9.2.dist-info/entry_points.txt
TopFM-0.9.2.dist-info/top_level.txt
TopFM-0.9.2.dist-info/RECORD
