Metadata-Version: 2.1
Name: TopFM
Version: 0.9.2
Summary: Last.fm collages
Home-page: https://github.com/nicfit/TopFM
Author: Travis Shirk
Author-email: travis@pobox.com
License: GNU GPL v3.0
Download-URL: https://github.com/nicfit/topfm/releases/downloads/v0.9.2/TopFM-0.9.2.tar.gz
Keywords: topfm
Platform: Any
Classifier: Intended Audience :: End Users/Desktop
Classifier: Operating System :: POSIX
Classifier: Natural Language :: English
Classifier: License :: OSI Approved :: GNU General Public License v3 (GPLv3)
Classifier: Programming Language :: Python
Classifier: Programming Language :: Python :: 3.6
Classifier: Programming Language :: Python :: 3.7
Classifier: Development Status :: 5 - Production/Stable
Requires-Dist: nicfit.py
Requires-Dist: Pillow
Requires-Dist: pylast
Requires-Dist: requests
